toon_converter/__init__.py
toon_converter/converter.py
toon_converter/exceptions.py
toon_token_optimizer-1.0.0.dist-info/licenses/LICENSE
toon_token_optimizer-1.0.0.dist-info/METADATA
toon_token_optimizer-1.0.0.dist-info/WHEEL
toon_token_optimizer-1.0.0.dist-info/top_level.txt
toon_token_optimizer-1.0.0.dist-info/RECORD
