Metadata-Version: 2.4
Name: toon-token-optimizer
Version: 1.0.0
Summary: Token Optimized Object Notation - Reduce LLM token usage by 40-60%
Home-page: https://github.com/prashantdudami/toon-converter
Author: Prashant Dudami
Author-email: Prashant Dudami <prashant.dudami@gmail.com>
License-Expression: MIT
Project-URL: Homepage, https://github.com/prashantdudami/toon-converter
Project-URL: Documentation, https://github.com/prashantdudami/toon-converter#readme
Project-URL: Repository, https://github.com/prashantdudami/toon-converter
Project-URL: Issues, https://github.com/prashantdudami/toon-converter/issues
Keywords: llm,tokens,json,optimization,ai,gpt,claude
Classifier: Development Status :: 4 - Beta
Classifier: Intended Audience :: Developers
Classifier: Operating System :: OS Independent
Classifier: Programming Language :: Python :: 3
Classifier: Programming Language :: Python :: 3.8
Classifier: Programming Language :: Python :: 3.9
Classifier: Programming Language :: Python :: 3.10
Classifier: Programming Language :: Python :: 3.11
Classifier: Programming Language :: Python :: 3.12
Classifier: Topic :: Scientific/Engineering :: Artificial Intelligence
Requires-Python: >=3.8
License-File: LICENSE
Provides-Extra: dev
Requires-Dist: pytest>=7.0.0; extra == "dev"
Requires-Dist: pytest-cov>=4.0.0; extra == "dev"
Dynamic: author
Dynamic: home-page
Dynamic: license-file
Dynamic: requires-python
